noisy_load_profiles/__init__.py
noisy_load_profiles/base.py
noisy_load_profiles/pipeline.py
noisy_load_profiles/utils.py
noisy_load_profiles/perturbations/__init__.py
noisy_load_profiles/perturbations/measurement.py
noisy_load_profiles/perturbations/random.py
noisy_load_profiles/perturbations/systematic.py
noisy_load_profiles-0.1.3.dist-info/METADATA
noisy_load_profiles-0.1.3.dist-info/WHEEL
noisy_load_profiles-0.1.3.dist-info/top_level.txt
noisy_load_profiles-0.1.3.dist-info/RECORD
