Metadata-Version: 2.4
Name: noisy_load_profiles
Version: 0.1.3
Summary: A Python package for adding realistic noise to electrical load or current profiles. Useful for studying robustness to noise of algorithms
Author-email: Flin Verdaasdonk <flin.verdaasdonk@gmail.com>
License-Expression: MIT
Project-URL: Homepage, https://github.com/flinverdaasdonk/noisy_load_profiles
Project-URL: Repository, https://github.com/flinverdaasdonk/noisy_load_profiles
Classifier: Development Status :: 3 - Alpha
Classifier: Programming Language :: Python :: 3
Classifier: Topic :: Scientific/Engineering
Requires-Python: >=3.12
Requires-Dist: numpy>=1.20.0
Provides-Extra: dev
